req_update/__init__.py
req_update/docker.py
req_update/drone.py
req_update/githubworkflow.py
req_update/gitsubmodule.py
req_update/go.py
req_update/node.py
req_update/py.typed
req_update/python.py
req_update/req_update.py
req_update/util.py
req_update-2.9.0.dist-info/licenses/LICENSE
req_update-2.9.0.dist-info/METADATA
req_update-2.9.0.dist-info/WHEEL
req_update-2.9.0.dist-info/entry_points.txt
req_update-2.9.0.dist-info/top_level.txt
req_update-2.9.0.dist-info/RECORD
