Metadata-Version: 2.4
Name: req-update
Version: 2.9.0
Summary: Update python, node, go, docker, and other dependencies
Author-email: Albert Wang <git@albertyw.com>
License-Expression: MIT
Project-URL: Homepage, https://github.com/albertyw/req-update
Keywords: dependencies
Classifier: Development Status :: 5 - Production/Stable
Classifier: Intended Audience :: Developers
Classifier: Natural Language :: English
Classifier: Topic :: Software Development :: Version Control
Classifier: Programming Language :: Python :: 3
Classifier: Programming Language :: Python :: 3.10
Classifier: Programming Language :: Python :: 3.11
Classifier: Programming Language :: Python :: 3.12
Classifier: Programming Language :: Python :: 3.13
Classifier: Programming Language :: Python :: 3.14
Classifier: Typing :: Typed
Requires-Python: >=3.10
License-File: LICENSE
Provides-Extra: test
Requires-Dist: coverage==7.13.0; extra == "test"
Requires-Dist: ruff==0.14.10; extra == "test"
Requires-Dist: mypy==1.19.1; extra == "test"
Dynamic: license-file
